bluetooth_locker/app.py
bluetooth_locker/checker.c
bluetooth_locker/checker.cpython-310-x86_64-linux-gnu.so
bluetooth_locker-0.1.6.dist-info/entry_points.txt
bluetooth_locker-0.1.6.dist-info/LICENSE
bluetooth_locker-0.1.6.dist-info/WHEEL
bluetooth_locker-0.1.6.dist-info/METADATA
bluetooth_locker-0.1.6.dist-info/RECORD
