Metadata-Version: 2.1
Name: bluetooth-locker
Version: 0.1.6
Summary: A bluetooth based locker
Home-page: https://github.com/leng-yue/bluetooth-locker
License: MIT
Author: leng-yue
Author-email: lengyue@lengyue.me
Requires-Python: >=3.8,<4.0
Classifier: License :: OSI Approved :: MIT License
Classifier: Programming Language :: Python :: 3
Classifier: Programming Language :: Python :: 3.10
Classifier: Programming Language :: Python :: 3.8
Classifier: Programming Language :: Python :: 3.9
Project-URL: Repository, https://github.com/leng-yue/bluetooth-locker
